rackio_modbus/__init__.py
rackio_modbus/_server.py
rackio_modbus/_singleton.py
rackio_modbus/api.py
rackio_modbus/client.py
rackio_modbus/core.py
rackio_modbus/decorator.py
rackio_modbus/server.py
rackio_modbus/worker.py
RackioModbus-0.2.dist-info/LICENSE
RackioModbus-0.2.dist-info/METADATA
RackioModbus-0.2.dist-info/WHEEL
RackioModbus-0.2.dist-info/top_level.txt
RackioModbus-0.2.dist-info/RECORD
