Metadata-Version: 2.1
Name: RackioModbus
Version: 0.2
Summary: A Rackio extension to enable Modbus TCP Server/Client integration
Home-page: https://github.com/rack-io/rackio-modbus
Author: Nelson Carrasquel
Author-email: rackio.framework@outlook.com
License: MIT
Platform: UNKNOWN
Classifier: Programming Language :: Python :: 3
Classifier: License :: OSI Approved :: MIT License
Classifier: Operating System :: OS Independent
Requires-Dist: umodbus
